reme/__init__.py
reme/__main__.py
reme/db.py
reme/entry.py
reme/reme.py
reme-1.0.3.dist-info/LICENSE
reme-1.0.3.dist-info/METADATA
reme-1.0.3.dist-info/WHEEL
reme-1.0.3.dist-info/entry_points.txt
reme-1.0.3.dist-info/top_level.txt
reme-1.0.3.dist-info/RECORD
