Metadata-Version: 2.1
Name: reme
Version: 1.0.3
Summary: A Discord bot that reminds you of things
Home-page: https://github.com/martinak1/reme
Author: martinak1
Author-email: abc000100100011@gmail.com
License: BSD-3-Clause
Platform: UNKNOWN
Classifier: License :: OSI Approved :: BSD License
Classifier: Programming Language :: Python :: 3
Classifier: Programming Language :: Python :: 3.7
Classifier: Programming Language :: Python :: 3.8
Classifier: Intended Audience :: End Users/Desktop
Classifier: Topic :: Communications :: Chat
Classifier: Topic :: Games/Entertainment
Requires-Dist: discord.py (>=1.3.1)
